multitude/__init__.py
multitude/graph.py
multitude/ordered_set.py
multitude-0.1.0.dist-info/DESCRIPTION.rst
multitude-0.1.0.dist-info/METADATA
multitude-0.1.0.dist-info/RECORD
multitude-0.1.0.dist-info/WHEEL
multitude-0.1.0.dist-info/metadata.json
multitude-0.1.0.dist-info/top_level.txt
